{"trial_id": "b8be633d1cd5658c1bfbdc878a963401", "hyperparameters": {"space": [{"class_name": "Int", "config": {"name": "layers", "default": null, "min_value": 1, "max_value": 2, "step": 1, "sampling": null}}, {"class_name": "Float", "config": {"name": "dropout", "default": 0.1, "min_value": 0.1, "max_value": 0.3, "step": 0.1, "sampling": null}}, {"class_name": "Int", "config": {"name": "neurons", "default": null, "min_value": 32, "max_value": 256, "step": 32, "sampling": null}}, {"class_name": "Int", "config": {"name": "batch_size", "default": null, "min_value": 1500, "max_value": 2000, "step": 100, "sampling": null}}], "values": {"layers": 2, "dropout": 0.1, "neurons": 160, "batch_size": 2000}}, "metrics": {"metrics": {"loss": {"direction": "min", "observations": [{"value": [0.010769885964691639], "step": 0}]}, "mse": {"direction": "min", "observations": [{"value": [0.010769885964691639], "step": 0}]}, "mape": {"direction": "min", "observations": [{"value": [8587.486328125], "step": 0}]}, "val_loss": {"direction": "min", "observations": [{"value": [0.01914973184466362], "step": 0}]}, "val_mse": {"direction": "min", "observations": [{"value": [0.01914973184466362], "step": 0}]}, "val_mape": {"direction": "min", "observations": [{"value": [54.51645278930664], "step": 0}]}}}, "score": 0.01914973184466362, "best_step": 0, "status": "COMPLETED"}